swagger_parser/__init__.py
swagger_parser/swagger_parser.py
swagger_parser-1.0.2.dist-info/AUTHORS.rst
swagger_parser-1.0.2.dist-info/LICENSE
swagger_parser-1.0.2.dist-info/METADATA
swagger_parser-1.0.2.dist-info/WHEEL
swagger_parser-1.0.2.dist-info/top_level.txt
swagger_parser-1.0.2.dist-info/RECORD
