Metadata-Version: 1.1
Name: swagger-parser
Version: 1.0.2
Summary: Swagger parser giving useful informations about your swagger files
Home-page: https://github.com/Trax-air/swagger-parser
Author: Cyprien Guillemot
Author-email: cyprien.guillemot@gmail.com
License: MIT
Keywords: swagger,parser,API,REST,swagger-parser
Platform: UNKNOWN
Classifier: Development Status :: 5 - Production/Stable
Classifier: Intended Audience :: Developers
Classifier: License :: OSI Approved :: MIT License
Classifier: Natural Language :: English
Classifier: Programming Language :: Python :: 3
